{
 "agenda": [{
    "name": "January",
    "numberOfDays": 31,
    "year": 2019,
    "monthNumber": 1,
    "firstDayOfMonth": 1,
    "events": []
  },
  {
    "name": "February",
    "numberOfDays": 28,
    "year": 2019,
    "monthNumber": 2,
    "firstDayOfMonth": 2,
    "events": []
  },
  {
    "name": "March",
    "numberOfDays": 31,
    "year": 2019,
    "monthNumber": 3,
    "firstDayOfMonth": 3,
    "events": []
  },
  {
    "name": "April",
    "numberOfDays": 30,
    "year": 2019,
    "monthNumber": 4,
    "firstDayOfMonth": 2,
    "events": []
  },
  {
    "name": "May",
    "numberOfDays": 31,
    "year": 2019,
    "monthNumber": 5,
    "firstDayOfMonth": 4,
    "events": []
  },
  {
    "name": "June",
    "numberOfDays": 30,
    "year": 2019,
    "monthNumber": 6,
    "firstDayOfMonth": 2,
    "events": []
  },
  {
    "name": "July",
    "numberOfDays": 31,
    "year": 2019,
    "monthNumber": 7,
    "firstDayOfMonth": 3,
    "events": []
  },
  {
    "name": "August",
    "numberOfDays": 31,
    "year": 2019,
    "monthNumber": 8,
    "firstDayOfMonth": 4,
    "events": []
  },
  {
    "name": "September",
    "numberOfDays": 30,
    "year": 2019,
    "monthNumber": 9,
    "firstDayOfMonth": 5,
    "events": []
  },
  {
    "name": "October",
    "numberOfDays": 31,
    "year": 2019,
    "monthNumber": 10,
    "firstDayOfMonth": 2,
    "events": []
  },
  {
    "name": "November",
    "numberOfDays": 30,
    "year": 2019,
    "monthNumber": 11,
    "firstDayOfMonth": 1,
    "events": []
  },
  {
    "name": "December",
    "numberOfDays": 31,
    "year": 2019,
    "monthNumber": 12,
    "firstDayOfMonth": 5,
    "events": []
  }
]
}